[
    {
        "name": "tłuszczek",
        "opis":"godny przeciwnik breja tłuszczu",
        "hp":1000,
        "itemy":
        [
            {
                "name":"długi glukogen",
                "hp":0,
                "atak":60,
                "szansa":30
            },
            {
                "name":"czepek tłuszczowy",
                "hp":0,
                "atak":200,
                "szansa":5
            },
            {
                "name":"tarcza opychu",
                "hp":50,
                "atak":0,
                "szansa":30
            }

        ]
    },
    {
        "name": "wódz frytek",
        "opis": "jeden z potężnych frytkowych wodzów",
        "hp": 5000,
        "itemy": [
            {
                "name": "armia frytek",
                "hp": 0,
                "atak": 500,
                "szansa": 1
            },
            {
                "name": "pałeczka wodza",
                "hp": 0,
                "atak": 10,
                "szansa": 50
            },
            {
                "name": "frytkownica",
                "hp": 50,
                "atak": 0,
                "szansa": 20
            }
        ]
    },
    {
        "name": "potężny węglowodan",
        "opis": "to najpotężniejszy gladiator, z jakim można się zmierzyć",
        "hp": 3000,
        "itemy": [
            {
                "name": "potężny cios węglowodana",
                "hp": 0,
                "atak": 1000,
                "szansa": 1
            },
            {
                "name": "tarcza węglowodanowa",
                "hp": 100,
                "atak": 0,
                "szansa": 30
            },
            {
                "name": "cios węglowodanowej pięści",
                "hp": 0,
                "atak": 10,
                "szansa": 50
            },
            {
                "name": "replikacja węglowodanowa",
                "hp": 10,
                "atak": 5,
                "szansa": 20
            }
        ]
    },
    {
        "name": "koronawirus",
        "opis": "jest to niepokonany przeciwnik",
        "hp": 10000,
        "itemy": [
            {
                "name": "COVID-19",
                "hp": 10,
                "atak": 20,
                "szansa": 100
            }
        ]
    },
    {
        "name": "burgerowy sumo",
        "opis": "nie masz szans z burgerowym sumo",
        "hp": 1000,
        "itemy": [
            {
                "name": "skok masy",
                "hp": 0,
                "atak": 100,
                "szansa": 10
            },
            {
                "name": "cios sumo",
                "hp": 0,
                "atak": 10,
                "szansa": 95
            },
            {
                "name": "fałda tłuszczu",
                "hp": 100,
                "atak": 0,
                "szansa": 15
            }
        ]
    },
    {
        "name": "fast food",
        "opis": "jeden z największych bossów żywieniowych współczesnego świata",
        "hp": 20000,
        "itemy": [
            {
                "name": "tłuszcz z frytek",
                "hp": 100,
                "atak": 0,
                "szansa": 20
            },
            {
                "name": "karząca ręka kasjerki",
                "hp": 0,
                "atak": 200,
                "szansa": 30
            },
            {
                "name": "sałatki z fast fooda",
                "hp": 0,
                "atak": 100,
                "szansa": 40
            }
        ]
    },
    {
        "name": "super fałda tłuszczu",
        "opis": "sabotujący Cię przeciwnik",
        "hp": 5500,
        "itemy": [
            {
                "name": "wnikanie",
                "hp": 0,
                "atak": 100,
                "szansa": 50
            },
            {
                "name": "autoregeneracja",
                "hp": 100,
                "atak": 0,
                "szansa": 5
            }
        ]
    },
    {
        "name": "ninja chipsy",
        "opis": "nie wiesz, kiedy uderzy",
        "hp": 800,
        "itemy": [
            {
                "name": "ziemniaczane shurikeny",
                "hp": 0,
                "atak": 100,
                "szansa": 30
            },
            {
                "name": "ziemniaczana katana",
                "hp": 0,
                "atak": 200,
                "szansa": 30
            },
            {
                "name": "ziemniaczany cios",
                "hp": 0,
                "atak": 500,
                "szansa": 1
            }
        ]
    },
    {
        "name": "król gazowanych napójów",
        "opis": "lepiej nie zakłócać spokoju króla gazowanych napojów",
        "hp": 5710,
        "itemy": [
            {
                "name": "berło bąbelkowe",
                "hp": 0,
                "atak": 60,
                "szansa": 70
            },
            {
                "name": "straż bąbelkowa",
                "hp": 0,
                "atak": 10,
                "szansa": 35
            },
            {
                "name": "bąbelkowa mikstura",
                "hp": 50,
                "atak": 50,
                "szansa": 30
            }
        ]
    },
    {
        "name": "szalona pizza",
        "opis": "z szaleńcami lepiej się nie zadawać",
        "hp": 5100,
        "itemy": [
            {
                "name": "pistolet serowy",
                "hp": 0,
                "atak": 60,
                "szansa": 30
            },
            {
                "name": "dyski salami",
                "hp": 0,
                "atak": 300,
                "szansa": 1
            },
            {
                "name": "ściana ketchupu",
                "hp": 50,
                "atak": 0,
                "szansa": 30
            }
        ]
    },
    {
        "name": "telewizor zombie",
        "opis": "lepiej uciekaj od hordy telewizorów zombie",
        "hp": 7000,
        "itemy": [
            {
                "name": "hipnoza",
                "hp": 0,
                "atak": 100,
                "szansa": 30
            },
            {
                "name": "wciągnięcie",
                "hp": 0,
                "atak": 200,
                "szansa": 15
            },
            {
                "name": "bezmózg",
                "hp": 75,
                "atak": 0,
                "szansa": 50
            }
        ]
    },
    {
        "name": "wysysacz portfela",
        "opis": "nie zdasz sobie sprawy, kiedy zastaniesz oskubany",
        "hp": 1000,
        "itemy": [
            {
                "name": "zagadanie",
                "hp": 0,
                "atak": 80,
                "szansa": 30
            },
            {
                "name": "szybka ucieczka",
                "hp": 50,
                "atak": 0,
                "szansa": 30
            }
        ]
    },
    {
        "name": "pasożyt joystick",
        "opis": "nie wiesz, kiedy wpadniesz w jego łapy",
        "hp": 3200,
        "itemy": [
            {
                "name": "szpony",
                "hp": 100,
                "atak": 0,
                "szansa": 60
            }
        ]
    },
    {
        "name": "alkohol-naukowiec",
        "opis": "nie wiesz kiedy jego intelekt Cię powali",
        "hp": 1000,
        "itemy": [
            {
                "name": "zaklęcie naukowca",
                "hp": 0,
                "atak": 100,
                "szansa": 30
            },
            {
                "name": "energia chemiczna",
                "hp": 0,
                "atak": 200,
                "szansa": 5
            },
            {
                "name": "akcja-rekacja",
                "hp": 100,
                "atak": 0,
                "szansa": 30
            }
        ]
    },
    {
        "name": "e-papieros hacker",
        "opis": "nie wiesz kiedy zhackuje Twoje ciało",
        "hp": 5000,
        "itemy": [
            {
                "name": "deszyfrator haseł",
                "hp": 0,
                "atak": 100,
                "szansa": 30
            },
            {
                "name": "zbieranie danych",
                "hp": 100,
                "atak": 0,
                "szansa": 5
            },
            {
                "name": "wyłączanie płuc",
                "hp": 0,
                "atak": 400,
                "szansa": 1
            }
        ]
    },
    {
        "name": "papieros eksterminacja",
        "opis": "nie wiesz kiedy wyciągnie spluwę",
        "hp": 1000,
        "itemy": [
            {
                "name": "dezintegracja płuc",
                "hp": 0,
                "atak": 500,
                "szansa": 1
            },
            {
                "name": "eksterminacja",
                "hp": 0,
                "atak": 50,
                "szansa": 30
            },
            {
                "name": "restart systemu",
                "hp": 20,
                "atak": 0,
                "szansa": 30
            }
        ]
    },
    {
        "name": "cyberpet",
        "opis": "milutki, ale jaki groźny",
        "hp": 8000,
        "itemy": [
            {
                "name": "cyber-drapnięcie",
                "hp": 0,
                "atak": 60,
                "szansa": 30
            },
            {
                "name": "pancerz bitów",
                "hp": 100,
                "atak": 0,
                "szansa": 30
            },
            {
                "name": "cyber-ryk",
                "hp": 0,
                "atak": 105,
                "szansa": 10
            }
        ]
    },
    {
        "name": "duszek wirusek",
        "opis": "niewidzialny, ale groźny",
        "hp": 950,
        "itemy": [
            {
                "name": "atak skrzeli",
                "hp": 0,
                "atak": 100,
                "szansa": 10
            },
            {
                "name": "wzomożone powielanie",
                "hp": 100,
                "atak": 0,
                "szansa": 15
            },
            {
                "name": "totalna dominacja",
                "hp": 100,
                "atak": 190,
                "szansa": 5
            }
        ]
    },
    {
        "name": "szybkie bakterie",
        "opis": "szybkie niczym wiatr",
        "hp": 100,
        "itemy": [
            {
                "name": "prędkość światła",
                "hp": 0,
                "atak": 100,
                "szansa": 10
            },
            {
                "name": "powielanie DNA",
                "hp": 50,
                "atak": 200,
                "szansa": 5
            },
            {
                "name": "szybka replikacja",
                "hp": 50,
                "atak": 0,
                "szansa": 30
            }
        ]
    },
    {
        "name": "niezdrowy styl życia",
        "opis": "największy boss świata",
        "hp": 100000,
        "itemy": [
            {
                "name": "armia węglowodanów-gladiatorów",
                "hp": 0,
                "atak": 600,
                "szansa": 15
            },
            {
                "name": "armia burgerowych sumo",
                "hp": 0,
                "atak": 650,
                "szansa": 15
            },
            {
                "name": "tarcza z szalonych pizz",
                "hp": 100,
                "atak": 0,
                "szansa": 15
            }
        ]
    }
]